neo4j_uploader/__init__.py
neo4j_uploader/_conversions.py
neo4j_uploader/_logger.py
neo4j_uploader/_n4j.py
neo4j_uploader/_queries.py
neo4j_uploader/_schema.py
neo4j_uploader/_upload_utils.py
neo4j_uploader/errors.py
neo4j_uploader/models.py
neo4j_uploader-0.6.0.dist-info/LICENSE.txt
neo4j_uploader-0.6.0.dist-info/METADATA
neo4j_uploader-0.6.0.dist-info/WHEEL
neo4j_uploader-0.6.0.dist-info/RECORD
