Metadata-Version: 2.1
Name: neo4j-uploader
Version: 0.6.0
Summary: 
Author: Jason Koo
Author-email: jalakoo@gmail.com
Requires-Python: >=3.9,<4.0
Classifier: Programming Language :: Python :: 3
Classifier: Programming Language :: Python :: 3.9
Classifier: Programming Language :: Python :: 3.10
Classifier: Programming Language :: Python :: 3.11
Classifier: Programming Language :: Python :: 3.12
Requires-Dist: neo4j-rust-ext (>=5.20.0.0,<6.0.0.0)
Requires-Dist: pydantic (>=2.5.2,<3.0.0)
